README.rst
setup.cfg
setup.py
PP6Generator/__init__.py
PP6Generator/core.py
PP6Generator/presentation.py
PP6Generator/slides.py
PP6Generator/text.py
PP6Generator.egg-info/PKG-INFO
PP6Generator.egg-info/SOURCES.txt
PP6Generator.egg-info/dependency_links.txt
PP6Generator.egg-info/not-zip-safe
PP6Generator.egg-info/requires.txt
PP6Generator.egg-info/top_level.txt