Metadata-Version: 1.2
Name: PP6Generator
Version: 0.1.0
Summary: A toolkit for generating ProPresenter6 files.
Home-page: https://github.com/kikeh/PP6Generator
Author: kikeh
Author-email: heisba@gmail.com
Maintainer: kikeh
License: MIT
Project-URL: Issues, https://github.com/kikeh/PP6Generator/issues
Platform: UNKNOWN
Classifier: Development Status :: 4 - Beta
Classifier: Environment :: Web Environment
Classifier: Intended Audience :: Developers
Classifier: License :: OSI Approved :: MIT License
Classifier: Operating System :: OS Independent
Classifier: Programming Language :: Python
Classifier: Programming Language :: Python :: 3.6
Classifier: Programming Language :: Python :: 3.7
Classifier: Programming Language :: Python :: 3.8
Classifier: Programming Language :: Python :: 3 :: Only
